[
    {
        "type": "polygon",
        "rings": [
            [
                "106.69922508756535",
                "10.779850217113811",
                "21.9"
            ],
            [
                "106.69922441802805",
                "10.779850830449673",
                "21.9"
            ],
            [
                "106.69922473020463",
                "10.779851159310764",
                "21.9"
            ],
            [
                "106.69922539974213",
                "10.779850545974908",
                "21.9"
            ]
        ],
        "symbol": {
            "type": "simple-fill",
            "color": [
                209,190,168
            ],
            "outline": {
                "color": [
                    255,
                    255,
                    255
                ],
                "width": 0.1
            }
        }
    },
    {
        "type": "polygon",
        "rings": [
            [
                "106.69922508756535",
                "10.779850217113811",
                "21.9"
            ],
            
            [
                "106.69922539974213",
                "10.779850545974908",
                "21.9"
            ],
            [
                "106.69922539974213",
                "10.779850545974908",
                "21.7"
            ],
            [
                "106.69922571191883",
                "10.779850874836",
                "21.5"
            ],
            [
                "106.69922571191883",
                "10.779850874836",
                "0"
            ],
            [
                "106.69922508756535",
                "10.779850217113811",
                "0"
            ]
        ],
        "symbol": {
            "type": "simple-fill",
            "color": [
                209,190,168
            ],
            "outline": {
                "color": [
                    255,
                    255,
                    255
                ],
                "width": 0.1
            }
        }
    },
    {
        "type": "polygon",
        "rings": [
            
            [
                "106.69922441802805",
                "10.779850830449673",
                "21.9"
            ],
            [
                "106.69922473020463",
                "10.779851159310764",
                "21.9"
            ],
            [
                "106.69922473020463",
                "10.779851159310764",
                "21.7"
            ],
            [
                "106.69922504238141",
                "10.779851488171861",
                "21.5"
            ],
            [
                "106.69922504238141",
                "10.779851488171861",
                "0"
            ],
            [
                "106.69922441802805",
                "10.779850830449673",
                "0"
            ]
        ],
        "symbol": {
            "type": "simple-fill",
            "color": [
                209,190,168
            ],
            "outline": {
                "color": [
                    255,
                    255,
                    255
                ],
                "width": 0.1
            }
        }
    },
    {
        "type": "polygon",
        "rings": [
            
            [
                "106.69922473020463",
                "10.779851159310764",
                "21.7"
            ],
            [
                "106.69922504238141",
                "10.779851488171861",
                "21.5"
            ],
            [
                "106.69922504238141",
                "10.779851488171861",
                "0"
            ],
            [
                "106.69922504238141",
                "10.779851488171861",
                "0"
            ],
            [
                "106.69922571191883",
                "10.779850874836",
                "21.5"
            ],
            [
                "106.69922539974213",
                "10.779850545974908",
                "21.7"
            ]
            
        ],
        "symbol": {
            "type": "simple-fill",
            "color": [
                209,190,168
            ],
            "outline": {
                "color": [
                    255,
                    255,
                    255
                ],
                "width": 0.1
            }
        }
    },
    {
        "type": "polygon",
        "rings": [
            
            [
                "106.69922473020463",
                "10.779851159310764",
                "21.9"
            ],
            [
                "106.69922473020463",
                "10.779851159310764",
                "21.7"
            ],
            [
                "106.69922539974213",
                "10.779850545974908",
                "21.7"
            ],
            [
                "106.69922539974213",
                "10.779850545974908",
                "21.9"
            ]
            
        ],
        "symbol": {
            "type": "simple-fill",
            "color": [
                209,190,168
            ],
            "outline": {
                "color": [
                    255,
                    255,
                    255
                ],
                "width": 0.1
            }
        }
    }
]